{
  "unversionedId": "features/game-commands",
  "id": "features/game-commands",
  "title": "Game Commands",
  "description": "Interesting Game Commands",
  "source": "@site/docs/features/game-commands.mdx",
  "sourceDirName": "features",
  "slug": "/features/game-commands",
  "permalink": "/docs/features/game-commands",
  "draft": false,
  "tags": [],
  "version": "current",
  "lastUpdatedBy": "๖ۣۜŇŇ_MyTツ",
  "lastUpdatedAt": 1680360132,
  "formattedLastUpdatedAt": "Apr 1, 2023",
  "frontMatter": {
    "id": "game-commands",
    "title": "Game Commands",
    "description": "Interesting Game Commands"
  },
  "sidebar": "docs",
  "previous": {
    "title": "Features",
    "permalink": "/docs/features"
  },
  "next": {
    "title": "Images Generating Commands",
    "permalink": "/docs/features/images-generating-commands"
  }
}