{
  "unversionedId": "style_guide",
  "id": "version-3.3/style_guide",
  "title": "Style Guide",
  "description": "You can write content using GitHub-flavored Markdown syntax.",
  "source": "@site/versioned_docs/version-3.3/style_guide.mdx",
  "sourceDirName": ".",
  "slug": "/style_guide",
  "permalink": "/docs/style_guide",
  "draft": false,
  "tags": [],
  "version": "3.3",
  "lastUpdatedBy": "Author",
  "lastUpdatedAt": 1539502055,
  "formattedLastUpdatedAt": "Oct 14, 2018",
  "frontMatter": {
    "id": "style_guide",
    "title": "Style Guide",
    "sidebar_label": "Style Guide"
  }
}